README.md
setup.cfg
setup.py
compressor_additional_compilers/__init__.py
compressor_additional_compilers/apps.py
compressor_additional_compilers/filters.py
compressor_additional_compilers/precompilers.py
django_compressor_additional_compilers.egg-info/PKG-INFO
django_compressor_additional_compilers.egg-info/SOURCES.txt
django_compressor_additional_compilers.egg-info/dependency_links.txt
django_compressor_additional_compilers.egg-info/requires.txt
django_compressor_additional_compilers.egg-info/top_level.txt