Metadata-Version: 1.1
Name: django-compressor-additional-compilers
Version: 0.7.1
Summary: Set of add-ons for django-compressor
Home-page: https://github.com/kazurrr/django-compressor-toolkit
Author: Karol Masuhr
Author-email: karol@masuhr.pl
License: MIT
Platform: UNKNOWN
Classifier: Framework :: Django
Classifier: Intended Audience :: Developers
Classifier: License :: OSI Approved :: MIT License
Classifier: Operating System :: OS Independent
Classifier: Programming Language :: Python :: 2
Classifier: Programming Language :: Python :: 3
